{
    
    "slots": [ "mmt_necklace/pendant" ],
    "materialSlotCount": 1,
    "displayType": "major",
    "glyph": {
        "textureX": 176,
        "textureY": 48
    },
    "translation": {
        "primaryAttributes": {
            "generic.armor": 1
        },
        "durability": 1,
        "integrity": 1,
        "magicCapacity": 1
    },
    "outcomes": [
        {
            "materials": ["tetra:stone/", "tetra:gem/" ],
            "countFactor": 1,
            "moduleKey": "mmt_necklace/pendant/shield",
            "moduleVariant": "shield/"
        }
    ]
}