[
    {
        "modules": ["sword/basic_blade"],
        "moduleVariants": ["basic_hilt/nether_star_rod"],
        "visibilityKey": "basic_hilt/nether_star_rod",
        "tools": {
            "cut": 1
        }
    },
    {
        "modules": ["sword/heavy_blade"],
        "moduleVariants": ["basic_hilt/nether_star_rod"],
        "visibilityKey": "basic_hilt/nether_star_rod",
        "tools": {
            "cut": 1
        }
    },
    {
        "modules": ["sword/short_blade"],
        "moduleVariants": ["basic_hilt/nether_star_rod"],
        "visibilityKey": "basic_hilt/nether_star_rod",
        "tools": {
            "cut": 1
        }
    },
    {
        "modules": ["sword/stonecutter"],
        "moduleVariants": ["basic_hilt/nether_star_rod"],
        "visibilityKey": "basic_hilt/nether_star_rod",
        "tools": {
            "pickaxe_dig": 1
        }
    },
    {
        "modules": ["sword/machete"],
        "moduleVariants": ["basic_hilt/nether_star_rod"],
        "visibilityKey": "basic_hilt/nether_star_rod",
        "tools": {
            "cut": 1
        }
    },
    {
        "modules": ["sword/throwing_knife"],
        "moduleVariants": ["basic_hilt/nether_star_rod"],
        "visibilityKey": "basic_hilt/nether_star_rod",
        "tools": {
            "cut": 1
        }
    }
]
