{
  "key": "slime_block",
  "category": "block_sole",
  "primary": 0,
  "secondary": 0,
  "tertiary": 0,
  "durability": 0,
  "integrityCost": 0,
  "integrityGain": 0,
  "magicCapacity": 0,
  "toolLevel": 0,
  "toolEfficiency": 0,
  "tints": {
    "glyph": "84c873"
  },
  "textures": [
    "slime_block"
  ],
  "material": {
    "items": [
      "minecraft:slime_block"
    ]
  },
  "attributes": {
    "**generic.movement_speed": -0.2
  },
  "effects" : {
    "more_mod_tetra:curios_feather_falling": 100,
    "more_mod_tetra:curios_jump": 1
  }
}