{
    "key": "legendary_monsters_long_stick_half",
    "category": "misc",
    "primary": 4,
    "secondary": 3,
    "tertiary": 4,
    "durability": 409,
    "integrityCost": 1,
    "integrityGain": 7,
    "magicCapacity": 150,
    "toolLevel": 0,
    "toolEfficiency": 0,
    "tints": {
        "glyph": "stick_glyph",
        "texture": "stick"
    },
    "attributes": {
        "forge:attack_range": 1,
        "forge:reach_distance": 1
    },
    "textures": [
        "crude",
        "default"
    ],
    "material": {
        "items": [ "legendary_monsters:long_stick_half" ]
    },
    "conditions": [
        {
            "type": "forge:mod_loaded",
            "modid": "legendary_monsters"
        }
    ]
}
