{
  "key": "graveyard_dark_iron_ingot",
  "category": "metal",
  "primary": 6,
  "secondary": 3.15,
  "tertiary": 4,
  "durability": 550,
  "integrityCost": 2,
  "integrityGain": 5,
  "magicCapacity": 84,
  "toolLevel": "minecraft:iron",
  "toolEfficiency": 5,
  "tints": {
    "glyph": "686868",
    "texture": "686868"
  },
  "textures": [
    "metal",
    "default"
  ],
  "material": {
    "items": [ "graveyard:dark_iron_ingot" ]
  },
  "effects" : {
    "more_mod_tetra:deep_dark_fantasy": 1
  },
  "requiredTools": {
    "hammer_dig": "minecraft:gold"
  },
  "conditions": [
    {
      "type": "forge:mod_loaded",
      "modid": "graveyard"
    }
  ]
}
